pynusmv_community/__init__.py
pynusmv_community/cmdline.py
pynusmv_community/core.py
pynusmv_community/dump.py
pynusmv_community/main.py
pynusmv_community/mining.py
pynusmv_community/test_it.py
pynusmv_community/visualization.py
pynusmv_community/data/graph_vis/index.html
pynusmv_community/data/graph_vis/main.js
pynusmv_community/data/graph_vis/lib/d3.layout.cloud.js
pynusmv_community/data/graph_vis/lib/d3.v4.min.js
pynusmv_community/data/graph_vis/styles/viz.css
pynusmv_community/data/table_vis/index.html
pynusmv_community/data/table_vis/main.js
pynusmv_community/data/table_vis/data/test.json
pynusmv_community/data/table_vis/lib/d3.layout.cloud.js
pynusmv_community/data/table_vis/lib/d3.v4.min.js
pynusmv_community/data/table_vis/styles/viz.css
pynusmv_community-1.0rc2.dist-info/DESCRIPTION.rst
pynusmv_community-1.0rc2.dist-info/METADATA
pynusmv_community-1.0rc2.dist-info/RECORD
pynusmv_community-1.0rc2.dist-info/WHEEL
pynusmv_community-1.0rc2.dist-info/entry_points.txt
pynusmv_community-1.0rc2.dist-info/metadata.json
pynusmv_community-1.0rc2.dist-info/top_level.txt
