Metadata-Version: 2.0
Name: pynusmv-community
Version: 1.0rc2
Summary: Tools to analyze and understand the community structure of BMC instances
Home-page: http://lvl.info.ucl.ac.be/Tools/PyNuSMV-community
Author: Xavier GILLARD
Author-email: xavier.gillard@uclouvain.be
License: UNKNOWN
Platform: UNKNOWN
Requires-Dist: argparse
Requires-Dist: cairocffi
Requires-Dist: concepts
Requires-Dist: matplotlib
Requires-Dist: pandas
Requires-Dist: pymining
Requires-Dist: pynusmv
Requires-Dist: python-igraph
Requires-Dist: wordcloud
